Metadata-Version: 2.1
Name: ScryfallCardGolf
Version: 0.1.0
Summary: Facilitate the Scryfall Card Golf games!
Home-page: https://github.com/zeldazach/scryfallcardgolf
Author: Zach Halpern
Author-email: zahalpern+pypi@gmail.com
License: GPL-3.0
Keywords: Magic: The Gathering,MTG,JSON,Card Games,Collectible,Trading Cards
Platform: UNKNOWN
Classifier: Programming Language :: Python :: 3 :: Only
Classifier: Programming Language :: Python :: 3.5
Classifier: Programming Language :: Python :: 3.6
Classifier: Programming Language :: Python :: 3.7
Classifier: License :: OSI Approved :: GNU General Public License v3 or later (GPLv3+)
